pluot/__init__.py
pluot-0.0.1.dist-info/METADATA
pluot-0.0.1.dist-info/WHEEL
pluot-0.0.1.dist-info/top_level.txt
pluot-0.0.1.dist-info/RECORD
