Metadata-Version: 2.1
Name: pluot
Version: 0.0.1
Summary: pluot
Classifier: Programming Language :: Python :: 3
Classifier: Operating System :: OS Independent
Requires-Python: >=3.7
